README.txt
disabled-sc-releaser.cfg
setup.cfg
setup.py
docs/HISTORY.txt
docs/INSTALL.txt
docs/LICENSE.GPL
docs/LICENSE.txt
sc/__init__.py
sc.object.dissect.egg-info/PKG-INFO
sc.object.dissect.egg-info/SOURCES.txt
sc.object.dissect.egg-info/dependency_links.txt
sc.object.dissect.egg-info/entry_points.txt
sc.object.dissect.egg-info/namespace_packages.txt
sc.object.dissect.egg-info/not-zip-safe
sc.object.dissect.egg-info/paster_plugins.txt
sc.object.dissect.egg-info/requires.txt
sc.object.dissect.egg-info/top_level.txt
sc/object/__init__.py
sc/object/dissect/README.txt
sc/object/dissect/__init__.py
sc/object/dissect/config.py
sc/object/dissect/configure.zcml
sc/object/dissect/dissect.py
sc/object/dissect/tests.py
sc/object/dissect/version.txt
sc/object/dissect/browser/__init__.py
sc/object/dissect/browser/configure.zcml
sc/object/dissect/docs/__init__.py
sc/object/dissect/docs/browser.txt
sc/object/dissect/locales/manual.pot
sc/object/dissect/locales/rebuildAll.sh
sc/object/dissect/locales/scobjectdissect.pot
sc/object/dissect/profiles/default/metadata.xml